{
  "Main": "Strona główna",
  "AuctionList": "Lista aukcji",
  "AddAuction": "Dodaj aukcję",
  "GroupProject": "2016 Projekt Grupowy",


  "State": "Status",
  "AuctionPending": "aukcja trwa",
  "AuctionWaiting": "oczekująca",
  "AuctionInactive": "zablokowana",
  "AuctionEnded": "zakończona",
  "Author": "Autor",
  "StartDate": "Data rozpoczęcia",
  "EndDate": "Data zakończenia",
  "AuthorWantsToBeAbleToEndTheAuctionBeforeEndDate": "Autor zastrzegł prawo do zakończenia aukcji przed czasem.",
  "CurrentPrice": "Aktualna cena",
  "EndPrice":  "Cena końcowa",
  "StartingPrice": "Cena wywoławcza",
  "LogInToBeAbleToBid": "Zaloguj się aby licytować",
  "YouAreTheAuthorOfThisAuctionAndThereforeCantBid": "Jako autor tej aukcji nie możesz licytować.",
  "TheFieldBidMustBeANumber": "Wpisz poprawną kwotę.",
  "YouMustEnterThePrice": "Wpisz kwotę.",
  "Bid": "Licytuj",
  "BuyNowFor": "Kup teraz za ",
  "AdminCantBid": "Jako administrator nie możesz licytować w aukcjach.",
  "ItemDescription": "Opis przedmiotu",
  "BuyOffers": "Oferty kupna",
  "Number": "Numer",
  "User": "Użytkownik",
  "BidValue": "Kwota",
  "Date": "Data",
  "NoBidsYet": "Jeszcze nie ma ofert kupna!",
  "AuctionHasntStarted": "Aukcja się jeszcze nie rozpoczęła."
}
